fastapi_sio/__init__.py
fastapi_sio/actors.py
fastapi_sio/applications.py
fastapi_sio/asyncapi.py
fastapi_sio/schemas/asyncapi.py
fastapi_sio/utils.py
fastapi_sio-0.6.0.dist-info/LICENSE
fastapi_sio-0.6.0.dist-info/METADATA
fastapi_sio-0.6.0.dist-info/WHEEL
fastapi_sio-0.6.0.dist-info/RECORD
