Metadata-Version: 2.1
Name: fastapi-sio
Version: 0.6.0
Summary: Socket.io for FastAPI with AsyncAPI documentation
License: Apache-2.0
Keywords: fastapi,socket.io,asyncapi
Author: Marian Hlavac
Author-email: m@marianhlavac.cz
Requires-Python: >=3.10,<4.0
Classifier: Development Status :: 3 - Alpha
Classifier: Framework :: FastAPI
Classifier: Intended Audience :: Developers
Classifier: License :: OSI Approved :: Apache Software License
Classifier: Programming Language :: Python :: 3
Classifier: Programming Language :: Python :: 3.10
Classifier: Programming Language :: Python :: 3.11
Classifier: Programming Language :: Python :: 3.12
Classifier: Topic :: Communications
Classifier: Topic :: Software Development :: Libraries
Requires-Dist: fastapi (>=0.111.0,<1.0.0)
Requires-Dist: packaging (>=24.1,<25.0)
Requires-Dist: pydantic (>=2.8.2,<3.0.0)
Requires-Dist: python-socketio (>=4.0.0,<6.0.0)
Requires-Dist: rfc3986 (>=2.0.0)
Requires-Dist: websockets (>=10.2,<11.0)
